{
    "Changes": [	
		///// VICTOR /////
		
		/// RIDGESIDE GATHERING
		{
			"Action": "EditData",
			"Target": "Data/Festivals/fall20",
			"When": {
				"Language": "en",
				"Hearts:Victor": "6, 7, 8",
				"HasMod":"Rafseazz.RSVCP"
			},
			"Entries": {
				"Victor": "{{i18n:Victor.Gathering.01}}"
			}
		},	
		{
			"Action": "EditData",
			"Target": "Data/Festivals/fall20",
			"When": {
				"Language": "en",
				"Relationship:Victor": "Dating, Engaged",
				"HasMod":"Rafseazz.RSVCP"
			},
			"Entries": {
				"Victor": "{{i18n:Victor.Gathering.02}}"
			}
		},	
		{
			"Action": "EditData",
			"Target": "Data/Festivals/fall20",
			"When": {
				"Language": "en",
				"Relationship:Victor": "Married",
				"HasMod":"Rafseazz.RSVCP"
			},
			"Entries": {
				"Victor": "{{i18n:Victor.Gathering.03}}"
			}
		},	
		{
			"Action": "EditData",
			"Target": "Data/Festivals/fall20",
			"When": {
				"Language": "en",
				"Relationship:Victor": "Married",
				"HasMod":"Rafseazz.RSVCP",
				"Year |contains=2":true
			},
			"Entries": {
				"Victor": "{{i18n:Victor.Gathering.04}}"
			}
		},	
			
		/// EMBER OF RESOLUTIONS
		{
			"Action": "EditData",
			"Target": "Data/Festivals/winter28",
			"When": {
				"Language": "en",
				"Relationship:Victor": "Dating",
				"HasMod":"Rafseazz.RSVCP"
			},
			"Entries": {
				"Victor": "{{i18n:Victor.Ember.01}}"
			}
		},		
		{
			"Action": "EditData",
			"Target": "Data/Festivals/winter28",
			"When": {
				"Language": "en",
				"Relationship:Victor": "Engaged",
				"HasMod":"Rafseazz.RSVCP"
			},
			"Entries": {
				"Victor": "{{i18n:Victor.Ember.02}}"
			}
		},	
		{
			"Action": "EditData",
			"Target": "Data/Festivals/winter28",
			"When": {
				"Language": "en",
				"Relationship:Victor": "Married",
				"HasMod":"Rafseazz.RSVCP"
			},
			"Entries": {
				"Victor": "{{i18n:Victor.Ember.03}}"
			}
		},	
    ]     
}