{
    "Changes": [
      {
      "Action": "EditData",
      "Target": "Characters/Dialogue/Donny",
      "Entries": {
            "Introduction": "{{i18n:Introduction_Donny}}",
            "Mon": "{{i18n:Mon_Donny}}",
            "Mon2": "{{i18n:Mon_2_Donny}}",
            "Tue": "{{i18n:Tue_Donny}}",
            "Tue2": "{{i18n:Tue_2_Donny}}",
            "Wed": "{{i18n:Wed_Donny}}",
            "Wed2": "{{i18n:Wed_2_Donny}}",
            "Thu": "{{i18n:Thu_Donny}}",
            "Fri": "{{i18n:Fri_Donny}}",
            "Fri2": "{{i18n:Fri_2_Donny}}",
            "Fri3": "{{i18n:Fri_3_Donny}}",
            "Sat": "{{i18n:Sat_Donny}}",
            "Sun": "{{i18n:Sun_Donny}}",
            "spring_10": "{{i18n:Spring_10_Donny}}",
            "spring_22": "{{i18n:Spring_22_Donny}}",
            "summer_10": "{{i18n:Summer_10_Donny}}",
            "summer_10_2": "{{i18n:Summer_10_Donny_2}}",
            "summer_15": "{{i18n:Summer_15_Donny}}",
            "summer_16": "{{i18n:Summer_16_Donny}}",
            "fall_2": "{{i18n:Fall_2_Donny}}",
            "fall_15": "{{i18n:Fall_15_Donny}}",
            "fall_26": "{{i18n:Fall_26_Donny}}",
            "fall_26_2": "{{i18n:Fall_26_Donny_2}}",
            "winter_11": "{{i18n:Winter_11_Donny}}",
            "winter_15": "{{i18n:Winter_15_Donny}}",
            "winter_15_2": "{{i18n:Winter_15_Donny_2}}",
            "winter_24": "{{i18n:Winter_24_Donny}}",
            "winter_24_2": "{{i18n:Winter_24_Donny_2}}",
//Gifts
            "AcceptBirthdayGift_Positive": "{{i18n:gifts.Donny.BDPos}}",
            "AcceptBirthdayGift_Negative": "{{i18n:gifts.Donny.BDNeg}}",
            "AcceptGift_(O)StardropTea": "{{i18n:gifts.Donny.stardroptea}}",
            },
        },
    ]
}